{"activatedMoleculePct": {"0.00": 0.36216643365144974, "0.20": 0.2524598424089648}, "activatedTokens": {"0.00": [{"token": "C", "type": "atom", "count": 1561524}, {"token": "N", "type": "atom", "count": 484410}, {"token": "(", "type": "ring", "count": 435096}, {"token": ")", "type": "ring", "count": 406406}, {"token": "1", "type": "branch", "count": 397182}, {"token": "2", "type": "branch", "count": 218337}, {"token": "[C@@H]", "type": "atom", "count": 211324}, {"token": "other-atom", "type": "atom", "count": 122032}, {"token": "other-bond", "type": "bond", "count": 71741}, {"token": "other-branch", "type": "branch", "count": 30484}, {"token": ".", "type": "disconnection", "count": 398}], "0.20": [{"token": "C", "type": "atom", "count": 862425}, {"token": "N", "type": "atom", "count": 220836}, {"token": "(", "type": "ring", "count": 172408}, {"token": "[C@@H]", "type": "atom", "count": 156877}, {"token": "1", "type": "branch", "count": 138916}, {"token": "2", "type": "branch", "count": 92558}, {"token": ")", "type": "ring", "count": 47977}, {"token": "other-atom", "type": "atom", "count": 31967}, {"token": "other-bond", "type": "bond", "count": 15585}, {"token": "other-branch", "type": "branch", "count": 13869}, {"token": ".", "type": "disconnection", "count": 3}]}}