{"activatedMoleculePct": {"0.00": 0.9333962193677756, "0.20": 0.5865106526647591}, "activatedTokens": {"0.00": [{"token": "C", "type": "atom", "count": 2570740}, {"token": "c", "type": "atom", "count": 1307395}, {"token": "1", "type": "branch", "count": 574547}, {"token": "O", "type": "atom", "count": 289594}, {"token": "(", "type": "ring", "count": 279512}, {"token": "2", "type": "branch", "count": 251624}, {"token": "other-atom", "type": "atom", "count": 251237}, {"token": ")", "type": "ring", "count": 137373}, {"token": "other-branch", "type": "branch", "count": 81740}, {"token": "other-bond", "type": "bond", "count": 49304}, {"token": ".", "type": "disconnection", "count": 32}], "0.20": [{"token": "C", "type": "atom", "count": 1038448}, {"token": "c", "type": "atom", "count": 246673}, {"token": "1", "type": "branch", "count": 192060}, {"token": "2", "type": "branch", "count": 86214}, {"token": "[C@H]", "type": "atom", "count": 57540}, {"token": "[C@@H]", "type": "atom", "count": 42771}, {"token": "other-ring", "type": "ring", "count": 30178}, {"token": "other-atom", "type": "atom", "count": 27102}, {"token": "3", "type": "branch", "count": 20696}, {"token": "other-bond", "type": "bond", "count": 16844}, {"token": "other-branch", "type": "branch", "count": 2697}, {"token": ".", "type": "disconnection", "count": 15}]}}