{"activatedMoleculePct": {"0.00": 0.9566833378129868, "0.20": 0.7009000075433947}, "activatedTokens": {"0.00": [{"token": "C", "type": "atom", "count": 1413702}, {"token": "c", "type": "atom", "count": 1106287}, {"token": "N", "type": "atom", "count": 265323}, {"token": "[C@@H]", "type": "atom", "count": 264380}, {"token": "[C@H]", "type": "atom", "count": 219356}, {"token": ")", "type": "ring", "count": 155603}, {"token": "(", "type": "ring", "count": 137718}, {"token": "other-atom", "type": "atom", "count": 125476}, {"token": "other-bond", "type": "bond", "count": 30040}, {"token": "other-branch", "type": "branch", "count": 14474}], "0.20": [{"token": "c", "type": "atom", "count": 471479}, {"token": "C", "type": "atom", "count": 412673}, {"token": "[C@@H]", "type": "atom", "count": 198194}, {"token": "[C@H]", "type": "atom", "count": 162458}, {"token": "N", "type": "atom", "count": 95675}, {"token": "other-atom", "type": "atom", "count": 39353}, {"token": "(", "type": "ring", "count": 13610}, {"token": "s", "type": "atom", "count": 12257}, {"token": "other-bond", "type": "bond", "count": 7436}, {"token": "other-ring", "type": "ring", "count": 2512}, {"token": "other-branch", "type": "branch", "count": 1105}]}}