{"activatedMoleculePct": {"0.00": 0.3142036262489628, "0.20": 0.1296379976168732}, "activatedTokens": {"0.00": [{"token": "O", "type": "atom", "count": 182627}, {"token": "[C@H]", "type": "atom", "count": 96096}, {"token": "C", "type": "atom", "count": 58062}, {"token": "n", "type": "atom", "count": 56937}, {"token": "other-atom", "type": "atom", "count": 38230}, {"token": "s", "type": "atom", "count": 37690}, {"token": "N", "type": "atom", "count": 37569}, {"token": "other-bond", "type": "bond", "count": 28214}, {"token": "=", "type": "bond", "count": 15895}, {"token": "other-branch", "type": "branch", "count": 13303}, {"token": "other-ring", "type": "ring", "count": 5948}, {"token": ".", "type": "disconnection", "count": 47}], "0.20": [{"token": "O", "type": "atom", "count": 89837}, {"token": "[C@H]", "type": "atom", "count": 31824}, {"token": "s", "type": "atom", "count": 17126}, {"token": "\\", "type": "bond", "count": 12636}, {"token": "other-atom", "type": "atom", "count": 12481}, {"token": "n", "type": "atom", "count": 11394}, {"token": "N", "type": "atom", "count": 8412}, {"token": "=", "type": "bond", "count": 8048}, {"token": "other-bond", "type": "bond", "count": 4122}, {"token": "other-branch", "type": "branch", "count": 1028}, {"token": "other-ring", "type": "ring", "count": 89}]}}