{"0.20": {"activatedMoleculePct": 0.10656399838000107, "activatedTokens": {"N": 102964, "C": 41614, "O": 13851, "=": 4460, "(": 2655, "n": 2460, "others": 1230, "1": 1116, "c": 842, "S": 807, "[C@@H]": 745, "2": 726, "[C@@]": 669, "[C@H]": 614}}, "0.00": {"activatedMoleculePct": 0.391784144663268, "activatedTokens": {"N": 342398, "C": 181810, "(": 62986, "O": 53844, "c": 51108, "1": 27933, "n": 18253, "=": 17713, "2": 8838, ")": 7870, "others": 5926, "[C@@H]": 5623, "[C@H]": 5400, "o": 5004, "S": 4503, "[C@@]": 2401}}}