{"activatedMoleculePct": {"0.00": 0.006766351772661126, "0.20": 0.0007265094662279292}, "activatedTokens": {"0.00": [{"token": ".", "type": "disconnection", "count": 2028}, {"token": "other-atom", "type": "atom", "count": 1708}, {"token": ")", "type": "ring", "count": 1449}, {"token": "1", "type": "branch", "count": 911}, {"token": "c", "type": "atom", "count": 875}, {"token": "C", "type": "atom", "count": 838}, {"token": "3", "type": "branch", "count": 727}, {"token": "n", "type": "atom", "count": 678}, {"token": "other-ring", "type": "ring", "count": 194}, {"token": "other-branch", "type": "branch", "count": 132}, {"token": "other-bond", "type": "bond", "count": 118}], "0.20": [{"token": ".", "type": "disconnection", "count": 637}, {"token": "n", "type": "atom", "count": 86}, {"token": "C", "type": "atom", "count": 55}, {"token": "[C@H]", "type": "atom", "count": 51}, {"token": "O", "type": "atom", "count": 41}, {"token": "other-atom", "type": "atom", "count": 38}, {"token": "3", "type": "branch", "count": 32}, {"token": "N", "type": "atom", "count": 29}, {"token": "other-branch", "type": "branch", "count": 21}, {"token": "other-bond", "type": "bond", "count": 13}, {"token": "other-ring", "type": "ring", "count": 13}]}}