{"activatedMoleculePct": {"0.00": 0.9968310418746288, "0.20": 0.7492487730998152}, "activatedTokens": {"0.00": [{"token": "C", "type": "atom", "count": 5288737}, {"token": "c", "type": "atom", "count": 3918592}, {"token": "(", "type": "ring", "count": 1815909}, {"token": "O", "type": "atom", "count": 1738336}, {"token": "N", "type": "atom", "count": 1254307}, {"token": "other-atom", "type": "atom", "count": 1131764}, {"token": "other-branch", "type": "branch", "count": 968411}, {"token": "1", "type": "branch", "count": 904211}, {"token": "n", "type": "atom", "count": 674745}, {"token": "other-ring", "type": "ring", "count": 470317}, {"token": "other-bond", "type": "bond", "count": 183453}, {"token": ".", "type": "disconnection", "count": 259}], "0.20": [{"token": "C", "type": "atom", "count": 1068572}, {"token": "c", "type": "atom", "count": 672014}, {"token": "N", "type": "atom", "count": 362144}, {"token": "other-atom", "type": "atom", "count": 234429}, {"token": "other-branch", "type": "branch", "count": 217245}, {"token": "O", "type": "atom", "count": 204323}, {"token": "n", "type": "atom", "count": 184249}, {"token": "(", "type": "ring", "count": 136407}, {"token": "[C@@H]", "type": "atom", "count": 95847}, {"token": "other-bond", "type": "bond", "count": 29372}, {"token": "other-ring", "type": "ring", "count": 7892}, {"token": ".", "type": "disconnection", "count": 76}]}}