{"0.20": {"activatedMoleculePct": 0.0013241220916734838, "activatedTokens": {".": 1171, "C": 163, "c": 129, "Cl": 96, "[C@H]": 87, "n": 81, "N": 57, "3": 50, "#": 41, "O": 37, "2": 34, "[C@]": 25, "[C@@H]": 25, "s": 23, "(": 21, "others": 21, "\\": 20, "1": 20, "F": 6, "5": 6, "[Si]": 6}}, "0.00": {"activatedMoleculePct": 0.008682227542471875, "activatedTokens": {".": 2390, "c": 2310, "C": 2211, "O": 1251, "n": 838, "(": 806, "[C@H]": 591, "N": 531, "2": 459, "Cl": 348, "#": 327, "s": 205, "3": 185, "[C@]": 143, "1": 139, "[C@@H]": 118, "others": 105, "\\": 91, "F": 74, "=": 49, "4": 36}}}