{"activatedMoleculePct": {"0.00": 0.6812600837975938, "0.20": 0.4623668828862346}, "activatedTokens": {"0.00": [{"token": "C", "type": "atom", "count": 2004039}, {"token": "other-atom", "type": "atom", "count": 4279}, {"token": "other-branch", "type": "branch", "count": 1451}, {"token": "other-ring", "type": "ring", "count": 161}, {"token": "other-bond", "type": "bond", "count": 74}, {"token": ".", "type": "disconnection", "count": 1}], "0.20": [{"token": "C", "type": "atom", "count": 1023464}, {"token": "other-atom", "type": "atom", "count": 387}, {"token": "other-branch", "type": "branch", "count": 102}, {"token": "other-ring", "type": "ring", "count": 6}, {"token": ".", "type": "disconnection", "count": 1}]}}