{"activatedMoleculePct": {"0.00": 0.3113774165411265, "0.20": 0.15284602027342242}, "activatedTokens": {"0.00": [{"token": "[C@H]", "type": "atom", "count": 473812}, {"token": "[C@@]", "type": "atom", "count": 21011}, {"token": "[C@]", "type": "atom", "count": 15586}, {"token": "other-atom", "type": "atom", "count": 271}, {"token": "other-bond", "type": "bond", "count": 164}, {"token": "other-branch", "type": "branch", "count": 95}, {"token": "other-ring", "type": "ring", "count": 4}], "0.20": [{"token": "[C@H]", "type": "atom", "count": 219114}, {"token": "[C@@]", "type": "atom", "count": 6643}, {"token": "[C@]", "type": "atom", "count": 3434}, {"token": "other-atom", "type": "atom", "count": 28}, {"token": "other-branch", "type": "branch", "count": 1}]}}