{"activatedMoleculePct": {"0.00": 0.6657126347466334, "0.20": 0.3459525293441714}, "activatedTokens": {"0.00": [{"token": "C", "type": "atom", "count": 1162725}, {"token": "c", "type": "atom", "count": 675242}, {"token": "[C@@H]", "type": "atom", "count": 167972}, {"token": "other-atom", "type": "atom", "count": 16123}, {"token": "n", "type": "atom", "count": 12542}, {"token": "[C@]", "type": "atom", "count": 11826}, {"token": "other-ring", "type": "ring", "count": 704}, {"token": "other-branch", "type": "branch", "count": 609}, {"token": "other-bond", "type": "bond", "count": 212}, {"token": ".", "type": "disconnection", "count": 4}], "0.20": [{"token": "C", "type": "atom", "count": 399550}, {"token": "c", "type": "atom", "count": 284885}, {"token": "[C@@H]", "type": "atom", "count": 74454}, {"token": "other-atom", "type": "atom", "count": 6855}, {"token": "other-ring", "type": "ring", "count": 29}, {"token": "other-branch", "type": "branch", "count": 6}, {"token": "other-bond", "type": "bond", "count": 1}]}}