[{"concept": "\\", "conceptType": "Token", "conceptTypeGroup": "bond", "metrics": [{"thresh": 0, "tPos": 12882, "precision": 0.05171, "recall": 0.99922, "f1Score": 0.09833}, {"thresh": 0.2, "tPos": 12866, "precision": 0.1113, "recall": 0.99798, "f1Score": 0.20026}, {"thresh": 0.5, "tPos": 12815, "precision": 0.42894, "recall": 0.99403, "f1Score": 0.59928}], "reviewed": false}, {"concept": "#", "conceptType": "Token", "conceptTypeGroup": "bond", "metrics": [{"thresh": 0.2, "tPos": 60946, "precision": 0.52721, "recall": 0.74572, "f1Score": 0.61771}], "reviewed": false}]