{"activatedMoleculePct": {"0.00": 0.3368931320687284, "0.20": 0.2780854131985971}, "activatedTokens": {"0.00": [{"token": "o", "type": "atom", "count": 174736}, {"token": "s", "type": "atom", "count": 159006}, {"token": "[nH]", "type": "atom", "count": 139715}, {"token": "#", "type": "bond", "count": 53208}, {"token": "other-atom", "type": "atom", "count": 2932}, {"token": "/", "type": "bond", "count": 2714}, {"token": "Br", "type": "atom", "count": 818}, {"token": "other-ring", "type": "ring", "count": 774}, {"token": ".", "type": "disconnection", "count": 735}, {"token": "other-branch", "type": "branch", "count": 185}, {"token": "other-bond", "type": "bond", "count": 163}], "0.20": [{"token": "o", "type": "atom", "count": 158451}, {"token": "s", "type": "atom", "count": 131773}, {"token": "[nH]", "type": "atom", "count": 122835}, {"token": "#", "type": "bond", "count": 16563}, {"token": "other-atom", "type": "atom", "count": 299}, {"token": ".", "type": "disconnection", "count": 260}, {"token": "other-bond", "type": "bond", "count": 174}, {"token": "other-branch", "type": "branch", "count": 4}]}}