{"0.20": {"activatedMoleculePct": 0.0008795744646569989, "activatedTokens": {"F": 430, "3": 374, "1": 202, ")": 91, "=": 68, "7": 38, "9": 22, "[Cl-]": 20, "[CH3-]": 15, "others": 13, "[V]": 11, "5": 10, "[Pd+2]": 8, "[Y]": 8, "[Zn+2]": 4, "[Ti+2]": 4, "[Ir+3]": 4, "[Pt+2]": 3, "%10": 3, "[H+]": 3, "[Cu+2]": 3, "[OH-]": 3, "[Zr]": 2, "[Sm+3]": 2, "[Ru+6]": 2, "[Ru]": 2, "[Zn]": 2, "[Mo+4]": 2, "[U+2]": 2, "[Fe]": 2, "[HH]": 2, "%11": 2, "%15": 2, "%16": 2, "%17": 2, "%18": 2, "[Ru+2]": 2, "[Re]": 1, "8": 1, "[Cu+]": 1, "[H]": 1, "[Sb]": 1, "[Rh]": 1, "[Gd+3]": 1, "[Au+3]": 1, "[Mn]": 1, "[Mg]": 1, "[Ce+3]": 1, "4": 1, "[Co]": 1, "[Zr+4]": 1, "[Mn+3]": 1, "[Sr+2]": 1, "[PdH2]": 1, "[Ba+2]": 1, "[Sb+5]": 1}}, "0.00": {"activatedMoleculePct": 0.010521204628861322, "activatedTokens": {"F": 5194, ")": 3616, "=": 3511, "3": 1772, "1": 1012, "others": 152, "7": 91, "c": 67, "5": 34, "9": 30, "[Cl-]": 26, "[CH3-]": 17, "[V]": 11}}}