{"activatedMoleculePct": {"0.00": 0.21940439406400752, "0.20": 0.17454389926126}, "activatedTokens": {"0.00": [{"token": "F", "type": "atom", "count": 552144}, {"token": "[O-]", "type": "atom", "count": 8471}, {"token": "other-branch", "type": "branch", "count": 293}, {"token": "other-atom", "type": "atom", "count": 124}, {"token": "other-ring", "type": "ring", "count": 116}], "0.20": [{"token": "F", "type": "atom", "count": 445428}, {"token": "other-atom", "type": "atom", "count": 310}, {"token": "other-branch", "type": "branch", "count": 2}]}}