{"activatedMoleculePct": {"0.00": 0.5596473792562506, "0.20": 0.5129003034202337}, "activatedTokens": {"0.00": [{"token": "n", "type": "atom", "count": 1671925}, {"token": "other-atom", "type": "atom", "count": 562}, {"token": "other-ring", "type": "ring", "count": 275}, {"token": "other-branch", "type": "branch", "count": 14}, {"token": "other-bond", "type": "bond", "count": 8}], "0.20": [{"token": "n", "type": "atom", "count": 1469709}, {"token": "other-atom", "type": "atom", "count": 4}, {"token": "other-bond", "type": "bond", "count": 1}]}}