{"activatedMoleculePct": {"0.00": 0.000712594466370741, "0.20": 0.0002753705234896183}, "activatedTokens": {"0.00": [{"token": "C", "type": "atom", "count": 966}, {"token": ")", "type": "ring", "count": 119}, {"token": "4", "type": "branch", "count": 97}, {"token": "(", "type": "ring", "count": 49}, {"token": "other-branch", "type": "branch", "count": 48}, {"token": "other-atom", "type": "atom", "count": 37}, {"token": "6", "type": "branch", "count": 26}, {"token": "5", "type": "branch", "count": 24}, {"token": "O", "type": "atom", "count": 15}], "0.20": [{"token": "C", "type": "atom", "count": 315}, {"token": "4", "type": "branch", "count": 68}, {"token": "other-atom", "type": "atom", "count": 37}, {"token": "other-branch", "type": "branch", "count": 20}, {"token": ")", "type": "ring", "count": 17}, {"token": "6", "type": "branch", "count": 17}, {"token": "5", "type": "branch", "count": 15}, {"token": "(", "type": "ring", "count": 13}, {"token": "7", "type": "branch", "count": 9}]}}