{"0.20": {"activatedMoleculePct": 0.004492347848631167, "activatedTokens": {"1": 996, "[C@H]": 907, "Br": 907, "#": 813, "O": 599, "S": 494, "2": 462, ")": 415, "[nH]": 402, "[O-]": 253, "n": 202, "C": 144, "[N+]": 113, "3": 89, "others": 67, "[N-]": 61, "4": 60, "[CH]": 25, "[V]": 21, "c": 14, "(": 13, "[C@@H]": 11, ".": 11, "[Br-]": 11, "[C@]": 9, "[NH2+]": 8, "%16": 8, "[NH+]": 8, "[CH3-]": 8, "N": 7, "[Cl-]": 7, "\\": 7, "I": 6}}, "0.00": {"activatedMoleculePct": 0.014886852741950722, "activatedTokens": {"[C@H]": 3408, ")": 3080, "Br": 2734, "1": 2596, "#": 2424, "O": 2100, "S": 1913, "[nH]": 1147, "2": 1112, "C": 950, "[O-]": 435, "n": 419, "others": 221, "[N+]": 215, "3": 136, "[N-]": 104, "4": 103, "(": 89, "[C@]": 68, "[C@@H]": 66, "c": 47, "[CH]": 28, "\\": 26, "[C@@]": 21}}}