{"activatedMoleculePct": {"0.00": 0.3440710748897969, "0.20": 0.33871599705002003}, "activatedTokens": {"0.00": [{"token": "3", "type": "branch", "count": 997704}, {"token": "other-ring", "type": "ring", "count": 598}, {"token": "other-atom", "type": "atom", "count": 557}, {"token": "other-bond", "type": "bond", "count": 334}, {"token": "other-branch", "type": "branch", "count": 215}], "0.20": [{"token": "3", "type": "branch", "count": 947353}, {"token": "other-atom", "type": "atom", "count": 21}, {"token": "other-branch", "type": "branch", "count": 1}]}}