{"activatedMoleculePct": {"0.00": 0.08779486067789485, "0.20": 0.06515808538390386}, "activatedTokens": {"0.00": [{"token": "#", "type": "bond", "count": 80953}, {"token": "[C@]", "type": "atom", "count": 44668}, {"token": "other-ring", "type": "ring", "count": 251}, {"token": "other-atom", "type": "atom", "count": 102}, {"token": "other-bond", "type": "bond", "count": 46}, {"token": "other-branch", "type": "branch", "count": 33}, {"token": ".", "type": "disconnection", "count": 2}], "0.20": [{"token": "#", "type": "bond", "count": 77326}, {"token": "[C@]", "type": "atom", "count": 15241}, {"token": "other-atom", "type": "atom", "count": 4}, {"token": "other-bond", "type": "bond", "count": 2}]}}