{"activatedMoleculePct": {"0.00": 0.6075926098168127, "0.20": 0.3013835171700113}, "activatedTokens": {"0.00": [{"token": ")", "type": "ring", "count": 1269048}, {"token": "c", "type": "atom", "count": 111921}, {"token": "(", "type": "ring", "count": 83252}, {"token": "O", "type": "atom", "count": 23899}, {"token": "1", "type": "branch", "count": 9917}, {"token": "other-atom", "type": "atom", "count": 9058}, {"token": "other-bond", "type": "bond", "count": 5008}, {"token": "2", "type": "branch", "count": 5003}, {"token": "other-branch", "type": "branch", "count": 473}], "0.20": [{"token": ")", "type": "ring", "count": 516174}, {"token": "(", "type": "ring", "count": 7777}, {"token": "c", "type": "atom", "count": 4936}, {"token": "other-atom", "type": "atom", "count": 2291}, {"token": "other-branch", "type": "branch", "count": 1194}, {"token": "other-bond", "type": "bond", "count": 407}]}}