{"activatedMoleculePct": {"0.00": 0.7581997798500549, "0.20": 0.5556230148238691}, "activatedTokens": {"0.00": [{"token": ")", "type": "ring", "count": 2673580}, {"token": "other-atom", "type": "atom", "count": 2282}, {"token": "other-ring", "type": "ring", "count": 216}, {"token": "other-branch", "type": "branch", "count": 23}], "0.20": [{"token": ")", "type": "ring", "count": 1417283}, {"token": "other-atom", "type": "atom", "count": 54}, {"token": "other-branch", "type": "branch", "count": 12}]}}