{"activatedMoleculePct": {"0.00": 0.06288627856511451, "0.20": 0.001736445508494375}, "activatedTokens": {"0.00": [{"token": "C", "type": "atom", "count": 122503}, {"token": "N", "type": "atom", "count": 31817}, {"token": "1", "type": "branch", "count": 7780}, {"token": "-", "type": "bond", "count": 6141}, {"token": "/", "type": "bond", "count": 3929}, {"token": "S", "type": "atom", "count": 3219}, {"token": "#", "type": "bond", "count": 3149}, {"token": "other-atom", "type": "atom", "count": 2705}, {"token": "other-branch", "type": "branch", "count": 1907}, {"token": "other-ring", "type": "ring", "count": 1243}, {"token": "other-bond", "type": "bond", "count": 867}], "0.20": [{"token": "other-atom", "type": "atom", "count": 827}, {"token": "N", "type": "atom", "count": 555}, {"token": "-", "type": "bond", "count": 547}, {"token": "C", "type": "atom", "count": 438}, {"token": "1", "type": "branch", "count": 312}, {"token": "4", "type": "branch", "count": 275}, {"token": "/", "type": "bond", "count": 154}, {"token": "#", "type": "bond", "count": 81}, {"token": "other-bond", "type": "bond", "count": 40}, {"token": "other-branch", "type": "branch", "count": 31}, {"token": "other-ring", "type": "ring", "count": 14}]}}