{"activatedMoleculePct": {"0.00": 0.08715770015811834, "0.20": 0.0017445015610432736}, "activatedTokens": {"0.00": [{"token": "(", "type": "ring", "count": 119910}, {"token": "N", "type": "atom", "count": 18173}, {"token": "[C@H]", "type": "atom", "count": 7955}, {"token": "c", "type": "atom", "count": 4365}, {"token": "-", "type": "bond", "count": 3051}, {"token": "Br", "type": "atom", "count": 2730}, {"token": "other-branch", "type": "branch", "count": 2611}, {"token": "S", "type": "atom", "count": 2593}, {"token": "other-atom", "type": "atom", "count": 1134}, {"token": ".", "type": "disconnection", "count": 9}], "0.20": [{"token": "N", "type": "atom", "count": 854}, {"token": "other-atom", "type": "atom", "count": 775}, {"token": "(", "type": "ring", "count": 708}, {"token": "S", "type": "atom", "count": 275}, {"token": "3", "type": "branch", "count": 186}, {"token": "1", "type": "branch", "count": 142}, {"token": "Br", "type": "atom", "count": 114}, {"token": "other-branch", "type": "branch", "count": 89}, {"token": "-", "type": "bond", "count": 88}, {"token": ".", "type": "disconnection", "count": 1}]}}