{"activatedMoleculePct": {"0.00": 0.075008440545966, "0.20": 0.05521691653856323}, "activatedTokens": {"0.00": [{"token": "[nH]", "type": "atom", "count": 81746}, {"token": "o", "type": "atom", "count": 11221}, {"token": "s", "type": "atom", "count": 4682}, {"token": "N", "type": "atom", "count": 2665}, {"token": "n", "type": "atom", "count": 2331}, {"token": "other-atom", "type": "atom", "count": 1592}, {"token": "O", "type": "atom", "count": 1203}, {"token": "F", "type": "atom", "count": 1139}, {"token": "other-branch", "type": "branch", "count": 111}, {"token": "other-bond", "type": "bond", "count": 95}], "0.20": [{"token": "[nH]", "type": "atom", "count": 71795}, {"token": "o", "type": "atom", "count": 3688}, {"token": "s", "type": "atom", "count": 1600}, {"token": "other-atom", "type": "atom", "count": 266}, {"token": "other-bond", "type": "bond", "count": 3}, {"token": "other-branch", "type": "branch", "count": 3}]}}