{"activatedMoleculePct": {"0.00": 0.5868599923980159, "0.20": 0.3163721691214435}, "activatedTokens": {"0.00": [{"token": "C", "type": "atom", "count": 1167137}, {"token": "other-atom", "type": "atom", "count": 532610}, {"token": "O", "type": "atom", "count": 400684}, {"token": "c", "type": "atom", "count": 383025}, {"token": "[C@@H]", "type": "atom", "count": 263440}, {"token": "1", "type": "branch", "count": 247006}, {"token": "2", "type": "branch", "count": 241874}, {"token": "=", "type": "bond", "count": 219119}, {"token": "other-branch", "type": "branch", "count": 117889}, {"token": "other-ring", "type": "ring", "count": 89289}, {"token": "other-bond", "type": "bond", "count": 77}, {"token": ".", "type": "disconnection", "count": 26}], "0.20": [{"token": "C", "type": "atom", "count": 433434}, {"token": "[C@@H]", "type": "atom", "count": 143697}, {"token": "other-atom", "type": "atom", "count": 133796}, {"token": "c", "type": "atom", "count": 102502}, {"token": "O", "type": "atom", "count": 101821}, {"token": "2", "type": "branch", "count": 98051}, {"token": "1", "type": "branch", "count": 82500}, {"token": "N", "type": "atom", "count": 74206}, {"token": "other-branch", "type": "branch", "count": 47092}, {"token": "other-bond", "type": "bond", "count": 44019}, {"token": "other-ring", "type": "ring", "count": 15970}, {"token": ".", "type": "disconnection", "count": 9}]}}