{"activatedMoleculePct": {"0.00": 0.38361823685233915, "0.20": 0.2708496132728592}, "activatedTokens": {"0.00": [{"token": "C", "type": "atom", "count": 877867}, {"token": "N", "type": "atom", "count": 7209}, {"token": "S", "type": "atom", "count": 6444}, {"token": "other-atom", "type": "atom", "count": 4468}, {"token": "other-bond", "type": "bond", "count": 361}, {"token": "other-branch", "type": "branch", "count": 24}, {"token": "other-ring", "type": "ring", "count": 1}], "0.20": [{"token": "C", "type": "atom", "count": 538373}, {"token": "other-atom", "type": "atom", "count": 2417}, {"token": "other-bond", "type": "bond", "count": 2}, {"token": "other-branch", "type": "branch", "count": 1}]}}