{"activatedMoleculePct": {"0.00": 0.5431017120576404, "0.20": 0.3051449613419333}, "activatedTokens": {"0.00": [{"token": "C", "type": "atom", "count": 886453}, {"token": "c", "type": "atom", "count": 352418}, {"token": "O", "type": "atom", "count": 293733}, {"token": "other-atom", "type": "atom", "count": 288071}, {"token": "2", "type": "branch", "count": 274359}, {"token": "1", "type": "branch", "count": 200744}, {"token": "3", "type": "branch", "count": 200243}, {"token": "=", "type": "bond", "count": 172456}, {"token": "other-ring", "type": "ring", "count": 94156}, {"token": "other-branch", "type": "branch", "count": 57034}, {"token": "other-bond", "type": "bond", "count": 1909}, {"token": ".", "type": "disconnection", "count": 148}], "0.20": [{"token": "C", "type": "atom", "count": 345336}, {"token": "c", "type": "atom", "count": 147309}, {"token": "2", "type": "branch", "count": 130520}, {"token": "other-atom", "type": "atom", "count": 124934}, {"token": "3", "type": "branch", "count": 112051}, {"token": "O", "type": "atom", "count": 90690}, {"token": "1", "type": "branch", "count": 61346}, {"token": "=", "type": "bond", "count": 39023}, {"token": "other-branch", "type": "branch", "count": 33648}, {"token": "other-ring", "type": "ring", "count": 20059}, {"token": "other-bond", "type": "bond", "count": 376}]}}