{"activatedMoleculePct": {"0.00": 0.774670013102071, "0.20": 0.47924358060776323}, "activatedTokens": {"0.00": [{"token": "1", "type": "branch", "count": 1146865}, {"token": "2", "type": "branch", "count": 902954}, {"token": "c", "type": "atom", "count": 485701}, {"token": "C", "type": "atom", "count": 453121}, {"token": "3", "type": "branch", "count": 281479}, {"token": "other-atom", "type": "atom", "count": 124609}, {"token": "N", "type": "atom", "count": 114693}, {"token": "n", "type": "atom", "count": 105938}, {"token": "other-bond", "type": "bond", "count": 85536}, {"token": "other-branch", "type": "branch", "count": 72082}, {"token": "other-ring", "type": "ring", "count": 176}, {"token": ".", "type": "disconnection", "count": 7}], "0.20": [{"token": "1", "type": "branch", "count": 456293}, {"token": "2", "type": "branch", "count": 448187}, {"token": "3", "type": "branch", "count": 130587}, {"token": "C", "type": "atom", "count": 87920}, {"token": "c", "type": "atom", "count": 76648}, {"token": "other-atom", "type": "atom", "count": 54981}, {"token": "4", "type": "branch", "count": 30949}, {"token": "N", "type": "atom", "count": 27317}, {"token": "other-bond", "type": "bond", "count": 19675}, {"token": "other-branch", "type": "branch", "count": 3984}, {"token": "other-ring", "type": "ring", "count": 24}, {"token": ".", "type": "disconnection", "count": 4}]}}