{"activatedMoleculePct": {"0.00": 0.9188316087277809, "0.20": 0.7310406296024777}, "activatedTokens": {"0.00": [{"token": "C", "type": "atom", "count": 3300283}, {"token": "c", "type": "atom", "count": 3052964}, {"token": "other-atom", "type": "atom", "count": 1261695}, {"token": "O", "type": "atom", "count": 1046477}, {"token": "1", "type": "branch", "count": 957032}, {"token": "2", "type": "branch", "count": 758232}, {"token": "N", "type": "atom", "count": 740999}, {"token": "=", "type": "bond", "count": 521486}, {"token": "other-branch", "type": "branch", "count": 316975}, {"token": "other-ring", "type": "ring", "count": 52731}, {"token": "other-bond", "type": "bond", "count": 50424}, {"token": ".", "type": "disconnection", "count": 4445}], "0.20": [{"token": "C", "type": "atom", "count": 1443720}, {"token": "c", "type": "atom", "count": 1378231}, {"token": "other-atom", "type": "atom", "count": 574762}, {"token": "O", "type": "atom", "count": 472499}, {"token": "1", "type": "branch", "count": 392972}, {"token": "2", "type": "branch", "count": 367472}, {"token": "N", "type": "atom", "count": 365044}, {"token": "=", "type": "bond", "count": 189280}, {"token": "other-branch", "type": "branch", "count": 156801}, {"token": "other-bond", "type": "bond", "count": 22183}, {"token": "other-ring", "type": "ring", "count": 8798}, {"token": ".", "type": "disconnection", "count": 2715}]}}