{"activatedMoleculePct": {"0.00": 0.2714179311617633, "0.20": 0.1386468614717822}, "activatedTokens": {"0.00": [{"token": "C", "type": "atom", "count": 469117}, {"token": "O", "type": "atom", "count": 3301}, {"token": "[C@@H]", "type": "atom", "count": 3182}, {"token": "other-atom", "type": "atom", "count": 2621}, {"token": "N", "type": "atom", "count": 2281}, {"token": "other-branch", "type": "branch", "count": 1837}, {"token": "other-bond", "type": "bond", "count": 183}, {"token": "other-ring", "type": "ring", "count": 21}], "0.20": [{"token": "C", "type": "atom", "count": 212662}, {"token": "other-atom", "type": "atom", "count": 1420}, {"token": "other-branch", "type": "branch", "count": 7}, {"token": "other-bond", "type": "bond", "count": 2}]}}