[{"concept": "Cl", "conceptType": "Token", "conceptTypeGroup": "atom", "metrics": [{"thresh": 0, "tPos": 152731, "precision": 0.10929, "recall": 0.8101, "f1Score": 0.1926}], "reviewed": false}, {"concept": "#", "conceptType": "Token", "conceptTypeGroup": "bond", "metrics": [{"thresh": 0, "tPos": 69511, "precision": 0.04974, "recall": 0.85052, "f1Score": 0.09399}], "reviewed": false}, {"concept": "[S@]", "conceptType": "Token", "conceptTypeGroup": "atom", "metrics": [{"thresh": 0, "tPos": 4260, "precision": 0.00305, "recall": 0.97706, "f1Score": 0.00608}, {"thresh": 0.2, "tPos": 3805, "precision": 0.00558, "recall": 0.87271, "f1Score": 0.01108}], "reviewed": false}, {"concept": "[S@@]", "conceptType": "Token", "conceptTypeGroup": "atom", "metrics": [{"thresh": 0, "tPos": 3780, "precision": 0.0027, "recall": 0.9519, "f1Score": 0.00539}, {"thresh": 0.2, "tPos": 3242, "precision": 0.00475, "recall": 0.81642, "f1Score": 0.00945}], "reviewed": false}, {"concept": "[N-]", "conceptType": "Token", "conceptTypeGroup": "atom", "metrics": [{"thresh": 0, "tPos": 2060, "precision": 0.00147, "recall": 0.86229, "f1Score": 0.00294}], "reviewed": false}]