[{"concept": "C", "conceptType": "Token", "conceptTypeGroup": "atom", "metrics": [{"thresh": 0, "tPos": 12610269, "precision": 0.25805, "recall": 0.95324, "f1Score": 0.40616}], "reviewed": false}, {"concept": "c", "conceptType": "Token", "conceptTypeGroup": "atom", "metrics": [{"thresh": 0, "tPos": 10205606, "precision": 0.20885, "recall": 0.98603, "f1Score": 0.34469}, {"thresh": 0.2, "tPos": 9281071, "precision": 0.23893, "recall": 0.8967, "f1Score": 0.37732}], "reviewed": false}, {"concept": "1", "conceptType": "Token", "conceptTypeGroup": "ring", "metrics": [{"thresh": 0, "tPos": 4018537, "precision": 0.08223, "recall": 0.98459, "f1Score": 0.15179}, {"thresh": 0.2, "tPos": 3643657, "precision": 0.0938, "recall": 0.89274, "f1Score": 0.16977}], "reviewed": false}, {"concept": "O", "conceptType": "Token", "conceptTypeGroup": "atom", "metrics": [{"thresh": 0, "tPos": 3157941, "precision": 0.06462, "recall": 0.91364, "f1Score": 0.12071}], "reviewed": false}, {"concept": "N", "conceptType": "Token", "conceptTypeGroup": "atom", "metrics": [{"thresh": 0, "tPos": 2649638, "precision": 0.05422, "recall": 0.97974, "f1Score": 0.10276}, {"thresh": 0.2, "tPos": 2381951, "precision": 0.06132, "recall": 0.88076, "f1Score": 0.11466}], "reviewed": false}, {"concept": "2", "conceptType": "Token", "conceptTypeGroup": "ring", "metrics": [{"thresh": 0, "tPos": 2629605, "precision": 0.05381, "recall": 0.98841, "f1Score": 0.10207}, {"thresh": 0.2, "tPos": 2459527, "precision": 0.06332, "recall": 0.92448, "f1Score": 0.11852}], "reviewed": false}, {"concept": "n", "conceptType": "Token", "conceptTypeGroup": "atom", "metrics": [{"thresh": 0, "tPos": 1483121, "precision": 0.03035, "recall": 0.87317, "f1Score": 0.05866}], "reviewed": false}, {"concept": "3", "conceptType": "Token", "conceptTypeGroup": "ring", "metrics": [{"thresh": 0, "tPos": 986692, "precision": 0.02019, "recall": 0.98345, "f1Score": 0.03957}, {"thresh": 0.2, "tPos": 911194, "precision": 0.02346, "recall": 0.9082, "f1Score": 0.04573}], "reviewed": false}, {"concept": "[C@H]", "conceptType": "Token", "conceptTypeGroup": "atom", "metrics": [{"thresh": 0, "tPos": 730662, "precision": 0.01495, "recall": 0.90557, "f1Score": 0.02942}], "reviewed": false}, {"concept": "[C@@H]", "conceptType": "Token", "conceptTypeGroup": "atom", "metrics": [{"thresh": 0, "tPos": 720820, "precision": 0.01475, "recall": 0.91288, "f1Score": 0.02903}], "reviewed": false}, {"concept": "F", "conceptType": "Token", "conceptTypeGroup": "atom", "metrics": [{"thresh": 0, "tPos": 570629, "precision": 0.01168, "recall": 0.99491, "f1Score": 0.02308}, {"thresh": 0.2, "tPos": 542261, "precision": 0.01396, "recall": 0.94545, "f1Score": 0.02751}], "reviewed": false}, {"concept": "S", "conceptType": "Token", "conceptTypeGroup": "atom", "metrics": [{"thresh": 0, "tPos": 230441, "precision": 0.00472, "recall": 0.96614, "f1Score": 0.00939}, {"thresh": 0.2, "tPos": 204435, "precision": 0.00526, "recall": 0.85711, "f1Score": 0.01046}], "reviewed": false}, {"concept": "4", "conceptType": "Token", "conceptTypeGroup": "ring", "metrics": [{"thresh": 0, "tPos": 200155, "precision": 0.0041, "recall": 0.98331, "f1Score": 0.00816}, {"thresh": 0.2, "tPos": 191895, "precision": 0.00494, "recall": 0.94273, "f1Score": 0.00983}], "reviewed": false}, {"concept": "Cl", "conceptType": "Token", "conceptTypeGroup": "atom", "metrics": [{"thresh": 0, "tPos": 186390, "precision": 0.00381, "recall": 0.98863, "f1Score": 0.0076}, {"thresh": 0.2, "tPos": 179106, "precision": 0.00461, "recall": 0.95, "f1Score": 0.00918}], "reviewed": false}, {"concept": "o", "conceptType": "Token", "conceptTypeGroup": "atom", "metrics": [{"thresh": 0, "tPos": 165415, "precision": 0.00339, "recall": 0.93308, "f1Score": 0.00675}], "reviewed": false}, {"concept": "-", "conceptType": "Token", "conceptTypeGroup": "bond", "metrics": [{"thresh": 0, "tPos": 164802, "precision": 0.00337, "recall": 0.89778, "f1Score": 0.00672}], "reviewed": false}, {"concept": "s", "conceptType": "Token", "conceptTypeGroup": "atom", "metrics": [{"thresh": 0, "tPos": 136000, "precision": 0.00278, "recall": 0.83126, "f1Score": 0.00555}], "reviewed": false}, {"concept": "[nH]", "conceptType": "Token", "conceptTypeGroup": "atom", "metrics": [{"thresh": 0, "tPos": 135975, "precision": 0.00278, "recall": 0.95422, "f1Score": 0.00555}, {"thresh": 0.2, "tPos": 114732, "precision": 0.00295, "recall": 0.80515, "f1Score": 0.00589}], "reviewed": false}, {"concept": "#", "conceptType": "Token", "conceptTypeGroup": "bond", "metrics": [{"thresh": 0, "tPos": 78833, "precision": 0.00161, "recall": 0.96458, "f1Score": 0.00322}, {"thresh": 0.2, "tPos": 71106, "precision": 0.00183, "recall": 0.87003, "f1Score": 0.00365}], "reviewed": false}, {"concept": "Br", "conceptType": "Token", "conceptTypeGroup": "atom", "metrics": [{"thresh": 0, "tPos": 65632, "precision": 0.00134, "recall": 0.94896, "f1Score": 0.00268}, {"thresh": 0.2, "tPos": 55795, "precision": 0.00144, "recall": 0.80673, "f1Score": 0.00287}], "reviewed": false}, {"concept": "[C@@]", "conceptType": "Token", "conceptTypeGroup": "atom", "metrics": [{"thresh": 0, "tPos": 50489, "precision": 0.00103, "recall": 0.99484, "f1Score": 0.00206}, {"thresh": 0.2, "tPos": 49754, "precision": 0.00128, "recall": 0.98036, "f1Score": 0.00256}], "reviewed": false}, {"concept": "[C@]", "conceptType": "Token", "conceptTypeGroup": "atom", "metrics": [{"thresh": 0, "tPos": 50211, "precision": 0.00103, "recall": 0.98364, "f1Score": 0.00205}, {"thresh": 0.2, "tPos": 48076, "precision": 0.00124, "recall": 0.94182, "f1Score": 0.00247}], "reviewed": false}, {"concept": "/", "conceptType": "Token", "conceptTypeGroup": "bond", "metrics": [{"thresh": 0, "tPos": 47371, "precision": 0.00097, "recall": 0.94664, "f1Score": 0.00194}, {"thresh": 0.2, "tPos": 41278, "precision": 0.00106, "recall": 0.82488, "f1Score": 0.00212}], "reviewed": false}, {"concept": "[O-]", "conceptType": "Token", "conceptTypeGroup": "atom", "metrics": [{"thresh": 0, "tPos": 33272, "precision": 0.00068, "recall": 0.99793, "f1Score": 0.00136}, {"thresh": 0.2, "tPos": 32216, "precision": 0.00083, "recall": 0.96626, "f1Score": 0.00166}], "reviewed": false}, {"concept": "[N+]", "conceptType": "Token", "conceptTypeGroup": "atom", "metrics": [{"thresh": 0, "tPos": 32171, "precision": 0.00066, "recall": 0.94782, "f1Score": 0.00132}], "reviewed": false}, {"concept": "5", "conceptType": "Token", "conceptTypeGroup": "ring", "metrics": [{"thresh": 0, "tPos": 21725, "precision": 0.00044, "recall": 0.80089, "f1Score": 0.00089}], "reviewed": false}, {"concept": "\\", "conceptType": "Token", "conceptTypeGroup": "bond", "metrics": [{"thresh": 0, "tPos": 11876, "precision": 0.00024, "recall": 0.92119, "f1Score": 0.00049}], "reviewed": false}, {"concept": ".", "conceptType": "Token", "conceptTypeGroup": "disconnection", "metrics": [{"thresh": 0, "tPos": 9378, "precision": 0.00019, "recall": 0.85911, "f1Score": 0.00038}], "reviewed": false}, {"concept": "6", "conceptType": "Token", "conceptTypeGroup": "ring", "metrics": [{"thresh": 0, "tPos": 4541, "precision": 9e-05, "recall": 0.89039, "f1Score": 0.00019}], "reviewed": false}, {"concept": "[S@]", "conceptType": "Token", "conceptTypeGroup": "atom", "metrics": [{"thresh": 0, "tPos": 4334, "precision": 9e-05, "recall": 0.99404, "f1Score": 0.00018}, {"thresh": 0.2, "tPos": 4248, "precision": 0.00011, "recall": 0.97431, "f1Score": 0.00022}], "reviewed": false}, {"concept": "[S@@]", "conceptType": "Token", "conceptTypeGroup": "atom", "metrics": [{"thresh": 0, "tPos": 3797, "precision": 8e-05, "recall": 0.95618, "f1Score": 0.00016}, {"thresh": 0.2, "tPos": 3542, "precision": 9e-05, "recall": 0.89197, "f1Score": 0.00018}], "reviewed": false}, {"concept": "P", "conceptType": "Token", "conceptTypeGroup": "atom", "metrics": [{"thresh": 0, "tPos": 2437, "precision": 5e-05, "recall": 0.99388, "f1Score": 0.0001}, {"thresh": 0.2, "tPos": 2417, "precision": 6e-05, "recall": 0.98573, "f1Score": 0.00012}], "reviewed": false}, {"concept": "[N-]", "conceptType": "Token", "conceptTypeGroup": "atom", "metrics": [{"thresh": 0, "tPos": 2388, "precision": 5e-05, "recall": 0.99958, "f1Score": 0.0001}, {"thresh": 0.2, "tPos": 2381, "precision": 6e-05, "recall": 0.99665, "f1Score": 0.00012}], "reviewed": false}, {"concept": "[Si]", "conceptType": "Token", "conceptTypeGroup": "atom", "metrics": [{"thresh": 0, "tPos": 1822, "precision": 4e-05, "recall": 0.85943, "f1Score": 7e-05}], "reviewed": false}, {"concept": "[n+]", "conceptType": "Token", "conceptTypeGroup": "atom", "metrics": [{"thresh": 0, "tPos": 1614, "precision": 3e-05, "recall": 0.93728, "f1Score": 7e-05}, {"thresh": 0.2, "tPos": 1465, "precision": 4e-05, "recall": 0.85075, "f1Score": 8e-05}], "reviewed": false}]