[{"concept": "[nH]", "conceptType": "Token", "conceptTypeGroup": "atom", "metrics": [{"thresh": 0.0, "tPos": 137787, "precision": 0.6609, "recall": 0.9669, "f1Score": 0.7851}, {"thresh": 0.2, "tPos": 121151, "precision": 0.7177, "recall": 0.8502, "f1Score": 0.7783}], "reviewed": false}, {"concept": "/", "conceptType": "Token", "conceptTypeGroup": "bond", "metrics": [{"thresh": 0.0, "tPos": 45364, "precision": 0.2176, "recall": 0.9065, "f1Score": 0.3509}], "reviewed": false}, {"concept": "\\", "conceptType": "Token", "conceptTypeGroup": "bond", "metrics": [{"thresh": 0.0, "tPos": 10618, "precision": 0.0509, "recall": 0.8236, "f1Score": 0.0959}], "reviewed": false}, {"concept": "[S@]", "conceptType": "Token", "conceptTypeGroup": "atom", "metrics": [{"thresh": 0.0, "tPos": 4304, "precision": 0.0206, "recall": 0.9872, "f1Score": 0.0404}, {"thresh": 0.2, "tPos": 4010, "precision": 0.0238, "recall": 0.9197, "f1Score": 0.0463}], "reviewed": false}]