[{"concept": "C", "conceptType": "Token", "conceptTypeGroup": "atom", "metrics": [{"thresh": 0.0, "tPos": 13227997, "precision": 0.8277, "recall": 0.9999, "f1Score": 0.9057}, {"thresh": 0.2, "tPos": 13195339, "precision": 0.8465, "recall": 0.9975, "f1Score": 0.9158}], "reviewed": false}, {"concept": "=", "conceptType": "Token", "conceptTypeGroup": "bond", "metrics": [{"thresh": 0.0, "tPos": 2386790, "precision": 0.1494, "recall": 0.9999, "f1Score": 0.2599}, {"thresh": 0.2, "tPos": 2386762, "precision": 0.1531, "recall": 0.9999, "f1Score": 0.2656}], "reviewed": false}]