[{"concept": "2", "conceptType": "Token", "conceptTypeGroup": "branch", "metrics": [{"thresh": 0.0, "tPos": 2026632, "precision": 0.4766, "recall": 0.7618, "f1Score": 0.5864}], "reviewed": false}, {"concept": "3", "conceptType": "Token", "conceptTypeGroup": "branch", "metrics": [{"thresh": 0.0, "tPos": 865552, "precision": 0.2036, "recall": 0.8627, "f1Score": 0.3294}], "reviewed": false}, {"concept": "4", "conceptType": "Token", "conceptTypeGroup": "branch", "metrics": [{"thresh": 0.0, "tPos": 164327, "precision": 0.0386, "recall": 0.8073, "f1Score": 0.0738}], "reviewed": false}]