[{"concept": "o", "conceptType": "Token", "conceptTypeGroup": "atom", "metrics": [{"thresh": 0.0, "tPos": 177265, "precision": 0.6338, "recall": 0.9999, "f1Score": 0.7759}, {"thresh": 0.2, "tPos": 177265, "precision": 0.6352, "recall": 0.9999, "f1Score": 0.7769}], "reviewed": false}, {"concept": "[C@]", "conceptType": "Token", "conceptTypeGroup": "atom", "metrics": [{"thresh": 0.0, "tPos": 51045, "precision": 0.1825, "recall": 1.0, "f1Score": 0.3087}, {"thresh": 0.2, "tPos": 51044, "precision": 0.1829, "recall": 1.0, "f1Score": 0.3093}], "reviewed": false}, {"concept": "[C@@]", "conceptType": "Token", "conceptTypeGroup": "atom", "metrics": [{"thresh": 0.0, "tPos": 50748, "precision": 0.1815, "recall": 0.9999, "f1Score": 0.3072}, {"thresh": 0.2, "tPos": 50730, "precision": 0.1818, "recall": 0.9996, "f1Score": 0.3076}], "reviewed": false}]