[{"concept": "[C@@H]", "conceptType": "Token", "conceptTypeGroup": "atom", "metrics": [{"thresh": 0, "tPos": 789582, "precision": 0.45912, "recall": 0.99996, "f1Score": 0.6293}, {"thresh": 0.2, "tPos": 789582, "precision": 0.48627, "recall": 0.99996, "f1Score": 0.65434}, {"thresh": 0.5, "tPos": 786747, "precision": 0.49989, "recall": 0.99637, "f1Score": 0.66576}], "reviewed": false}, {"concept": "F", "conceptType": "Token", "conceptTypeGroup": "atom", "metrics": [{"thresh": 0, "tPos": 573507, "precision": 0.33348, "recall": 0.99992, "f1Score": 0.50015}, {"thresh": 0.2, "tPos": 573507, "precision": 0.3532, "recall": 0.99992, "f1Score": 0.52201}, {"thresh": 0.5, "tPos": 573491, "precision": 0.36439, "recall": 0.9999, "f1Score": 0.53413}], "reviewed": false}, {"concept": "4", "conceptType": "Token", "conceptTypeGroup": "ring", "metrics": [{"thresh": 0, "tPos": 203543, "precision": 0.11835, "recall": 0.99996, "f1Score": 0.21166}, {"thresh": 0.2, "tPos": 203543, "precision": 0.12535, "recall": 0.99996, "f1Score": 0.22278}, {"thresh": 0.5, "tPos": 198754, "precision": 0.12629, "recall": 0.97643, "f1Score": 0.22365}], "reviewed": false}, {"concept": "#", "conceptType": "Token", "conceptTypeGroup": "bond", "metrics": [{"thresh": 0, "tPos": 73695, "precision": 0.04285, "recall": 0.90171, "f1Score": 0.08181}], "reviewed": false}, {"concept": "[O-]", "conceptType": "Token", "conceptTypeGroup": "atom", "metrics": [{"thresh": 0, "tPos": 33181, "precision": 0.01929, "recall": 0.9952, "f1Score": 0.03785}], "reviewed": false}, {"concept": "5", "conceptType": "Token", "conceptTypeGroup": "ring", "metrics": [{"thresh": 0, "tPos": 27126, "precision": 0.01577, "recall": 1.0, "f1Score": 0.03106}, {"thresh": 0.2, "tPos": 27126, "precision": 0.01671, "recall": 1.0, "f1Score": 0.03286}], "reviewed": false}, {"concept": "6", "conceptType": "Token", "conceptTypeGroup": "ring", "metrics": [{"thresh": 0, "tPos": 5100, "precision": 0.00297, "recall": 1.0, "f1Score": 0.00591}, {"thresh": 0.2, "tPos": 5100, "precision": 0.00314, "recall": 1.0, "f1Score": 0.00626}], "reviewed": false}]