[{"concept": "-", "conceptType": "Token", "conceptTypeGroup": "bond", "metrics": [{"thresh": 0.0, "tPos": 183560, "precision": 0.6344, "recall": 1.0, "f1Score": 0.7763}, {"thresh": 0.2, "tPos": 183547, "precision": 0.9159, "recall": 0.9999, "f1Score": 0.9561}], "reviewed": false}, {"concept": "6", "conceptType": "Token", "conceptTypeGroup": "branch", "metrics": [{"thresh": 0.0, "tPos": 5100, "precision": 0.0176, "recall": 1.0, "f1Score": 0.0346}, {"thresh": 0.2, "tPos": 5100, "precision": 0.0255, "recall": 1.0, "f1Score": 0.0496}], "reviewed": false}, {"concept": "[Si]", "conceptType": "Token", "conceptTypeGroup": "atom", "metrics": [{"thresh": 0.0, "tPos": 2062, "precision": 0.0071, "recall": 0.9726, "f1Score": 0.0141}, {"thresh": 0.2, "tPos": 2009, "precision": 0.01, "recall": 0.9476, "f1Score": 0.0198}], "reviewed": false}]