[{"concept": "1", "conceptType": "Token", "conceptTypeGroup": "ring", "metrics": [{"thresh": 0, "tPos": 4081186, "precision": 0.94979, "recall": 0.99994, "f1Score": 0.97422}, {"thresh": 0.2, "tPos": 4081186, "precision": 0.95118, "recall": 0.99994, "f1Score": 0.97495}, {"thresh": 0.5, "tPos": 3838861, "precision": 0.96253, "recall": 0.94057, "f1Score": 0.95142}], "reviewed": false}, {"concept": "4", "conceptType": "Token", "conceptTypeGroup": "ring", "metrics": [{"thresh": 0, "tPos": 203543, "precision": 0.04737, "recall": 0.99996, "f1Score": 0.09045}, {"thresh": 0.2, "tPos": 203541, "precision": 0.04744, "recall": 0.99995, "f1Score": 0.09058}], "reviewed": false}, {"concept": "6", "conceptType": "Token", "conceptTypeGroup": "ring", "metrics": [{"thresh": 0, "tPos": 5100, "precision": 0.00119, "recall": 1.0, "f1Score": 0.00237}, {"thresh": 0.2, "tPos": 5100, "precision": 0.00119, "recall": 1.0, "f1Score": 0.00237}], "reviewed": false}, {"concept": "[N-]", "conceptType": "Token", "conceptTypeGroup": "atom", "metrics": [{"thresh": 0, "tPos": 2231, "precision": 0.00052, "recall": 0.93386, "f1Score": 0.00104}], "reviewed": false}]