[{"concept": "F", "conceptType": "Token", "conceptTypeGroup": "atom", "metrics": [{"thresh": 0.0, "tPos": 565011, "precision": 0.7025, "recall": 0.9851, "f1Score": 0.8201}, {"thresh": 0.2, "tPos": 479280, "precision": 0.6822, "recall": 0.8356, "f1Score": 0.7512}], "reviewed": false}, {"concept": "S", "conceptType": "Token", "conceptTypeGroup": "atom", "metrics": [{"thresh": 0.0, "tPos": 236780, "precision": 0.2944, "recall": 0.9927, "f1Score": 0.4541}, {"thresh": 0.2, "tPos": 222269, "precision": 0.3164, "recall": 0.9319, "f1Score": 0.4724}], "reviewed": false}]